[
    {
        "S1": [
            0.5750189833755981,
            0.0034906329103054174,
            0.00041750998616785044,
            -0.0031765867601559685
        ],
        "S1_conf": [
            0.3142522461265747,
            0.011707802743560527,
            0.013263419292125501,
            0.07791609265308984
        ],
        "ST": [
            0.7413932591078143,
            0.0024647956776913246,
            0.0020922460955134278,
            0.16066045996687983
        ],
        "ST_conf": [
            0.2096073675218419,
            0.001399292147799692,
            0.0009852685509704425,
            0.1118406367652718
        ],
        "S2": [
            [
                NaN,
                0.0782445355986759,
                0.07703916358875607,
                0.22709716637979138
            ],
            [
                NaN,
                NaN,
                -0.007872532832027747,
                -0.0181498418765247
            ],
            [
                NaN,
                NaN,
                NaN,
                -0.00907121017262842
            ],
            [
                NaN,
                NaN,
                NaN,
                NaN
            ]
        ],
        "S2_conf": [
            [
                NaN,
                0.549854635035388,
                0.5527059010794794,
                0.5855403463227558
            ],
            [
                NaN,
                NaN,
                0.022294170759265552,
                0.022330018751538675
            ],
            [
                NaN,
                NaN,
                NaN,
                0.02511458443712852
            ],
            [
                NaN,
                NaN,
                NaN,
                NaN
            ]
        ]
    },
    {
        "S1": [
            0.21361023219749875,
            -0.0076708081793003206,
            0.7573770368890821,
            -0.008730047964989916
        ],
        "S1_conf": [
            0.14438833539319856,
            0.022264274158988104,
            0.3143474203292194,
            0.021402328028095628
        ],
        "ST": [
            0.2684511539441852,
            0.006034819911788119,
            0.8573368731485067,
            0.005799442839255255
        ],
        "ST_conf": [
            0.1236446531437507,
            0.002344008589105561,
            0.21546229366593297,
            0.0025300785352399065
        ],
        "S2": [
            [
                NaN,
                -0.03591749385983629,
                0.052748513525010754,
                -0.034572110526158495
            ],
            [
                NaN,
                NaN,
                0.012966639876573649,
                -0.002727321142240653
            ],
            [
                NaN,
                NaN,
                NaN,
                0.026763701014910577
            ],
            [
                NaN,
                NaN,
                NaN,
                NaN
            ]
        ],
        "S2_conf": [
            [
                NaN,
                0.1583795998115155,
                0.20012642330758143,
                0.155758502445295
            ],
            [
                NaN,
                NaN,
                0.03014232238402945,
                0.02812795178153149
            ],
            [
                NaN,
                NaN,
                NaN,
                0.3692569552448318
            ],
            [
                NaN,
                NaN,
                NaN,
                NaN
            ]
        ]
    }
]